de_escalation_scoring/__init__.py
de_escalation_scoring/core.py
de_escalation_scoring_module-0.1.1.dist-info/licenses/LICENSE
de_escalation_scoring_module-0.1.1.dist-info/METADATA
de_escalation_scoring_module-0.1.1.dist-info/WHEEL
de_escalation_scoring_module-0.1.1.dist-info/top_level.txt
de_escalation_scoring_module-0.1.1.dist-info/RECORD
