Metadata-Version: 2.4
Name: de-escalation-scoring-module
Version: 0.1.1
Summary: AI-powered module for evaluating escalation and de-escalation patterns in chat conversations
Author-email: Yuan Xu <dev.source@example.com>
License: MIT
Project-URL: Homepage, https://github.dev/NewJerseyStyle/DeEscalationScoringModule
Project-URL: Repository, https://github.com/NewJerseyStyle/DeEscalationScoringModule.git
Project-URL: Bug Tracker, https://github.com/NewJerseyStyle/DeEscalationScoringModule/issues
Keywords: ai,chatbot,conversation-analysis,customer-service,de-escalation,escalation-detection,nlp,openai,sentiment-analysis
Classifier: Development Status :: 4 - Beta
Classifier: Intended Audience :: Developers
Classifier: Intended Audience :: Customer Service
Classifier: License :: OSI Approved :: MIT License
Classifier: Operating System :: OS Independent
Classifier: Programming Language :: Python :: 3
Classifier: Programming Language :: Python :: 3.10
Classifier: Programming Language :: Python :: 3.11
Classifier: Programming Language :: Python :: 3.12
Classifier: Topic :: Communications :: Chat
Classifier: Topic :: Scientific/Engineering :: Artificial Intelligence
Classifier: Topic :: Software Development :: Libraries :: Python Modules
Classifier: Topic :: Text Processing :: Linguistic
Classifier: Typing :: Typed
Requires-Python: >=3.10
License-File: LICENSE
Requires-Dist: json-repair>=0.25.0
Requires-Dist: openai>=1.0.0
Dynamic: license-file
